docmind/__init__.py
docmind/__main__.py
docmind/cli.py
docmind/config.py
docmind/converter.py
docmind/exceptions.py
docmind-1.0.0.dist-info/METADATA
docmind-1.0.0.dist-info/WHEEL
docmind-1.0.0.dist-info/entry_points.txt
docmind-1.0.0.dist-info/top_level.txt
docmind-1.0.0.dist-info/RECORD
