Metadata-Version: 2.4
Name: docmind
Version: 1.0.0
Summary: AI-optimized document converter for technical documents
Home-page: https://github.com/mount-agency/docmind
Author: Mount
Author-email: Mount <simon@mount.agency>
Project-URL: Homepage, https://github.com/mount-agency/docmind
Project-URL: Repository, https://github.com/mount-agency/docmind
Project-URL: Issues, https://github.com/mount-agency/docmind/issues
Keywords: pdf,docx,markdown,converter,ai,llm
Classifier: Development Status :: 4 - Beta
Classifier: Intended Audience :: Developers
Classifier: License :: OSI Approved :: MIT License
Classifier: Programming Language :: Python :: 3
Classifier: Topic :: Text Processing :: Markup
Requires-Python: >=3.7
Requires-Dist: Pillow>=10.0.0
Requires-Dist: pdfplumber>=0.9.0
Requires-Dist: python-docx>=0.8.11
Requires-Dist: PyMuPDF>=1.23.0
Requires-Dist: PyYAML>=6.0
Requires-Dist: tqdm>=4.64.0
Requires-Dist: pytesseract>=0.3.10
Provides-Extra: full
Requires-Dist: tqdm>=4.64.0; extra == "full"
Requires-Dist: pytesseract>=0.3.10; extra == "full"
Provides-Extra: ocr
Requires-Dist: pytesseract>=0.3.10; extra == "ocr"
Provides-Extra: progress
Requires-Dist: tqdm>=4.64.0; extra == "progress"
Dynamic: author
Dynamic: home-page
Dynamic: requires-python
